csv_cleaner/__init__.py
csv_cleaner/_version.py
csv_cleaner/feature_gate.py
csv_cleaner/cli/__init__.py
csv_cleaner/cli/commands.py
csv_cleaner/cli/decorators.py
csv_cleaner/cli/main.py
csv_cleaner/cli/utils.py
csv_cleaner/core/__init__.py
csv_cleaner/core/ai_agent.py
csv_cleaner/core/ai_logging.py
csv_cleaner/core/ai_utils.py
csv_cleaner/core/cleaner.py
csv_cleaner/core/config.py
csv_cleaner/core/config_factory.py
csv_cleaner/core/file_operations.py
csv_cleaner/core/library_manager.py
csv_cleaner/core/llm_providers.py
csv_cleaner/core/parallel_processor.py
csv_cleaner/core/performance_manager.py
csv_cleaner/core/temp_file_manager.py
csv_cleaner/core/validator.py
csv_cleaner/core/visualization_manager.py
csv_cleaner/utils/__init__.py
csv_cleaner/utils/temp_utils.py
csv_cleaner/wrappers/__init__.py
csv_cleaner/wrappers/base.py
csv_cleaner/wrappers/dedupe_wrapper.py
csv_cleaner/wrappers/feature_engine_wrapper.py
csv_cleaner/wrappers/missingno_wrapper.py
csv_cleaner/wrappers/pandas_wrapper.py
csv_cleaner/wrappers/pyjanitor_wrapper.py
csv_data_cleaner-0.1.0.dist-info/licenses/LICENSE
csv_data_cleaner-0.1.0.dist-info/METADATA
csv_data_cleaner-0.1.0.dist-info/WHEEL
csv_data_cleaner-0.1.0.dist-info/entry_points.txt
csv_data_cleaner-0.1.0.dist-info/top_level.txt
csv_data_cleaner-0.1.0.dist-info/RECORD
