Metadata-Version: 2.4
Name: csv-data-cleaner
Version: 0.1.0
Summary: Self-contained CSV data cleaning tool with AI capabilities
Author-email: Faizal <jai.crys@gmail.com>
Maintainer-email: Faizal <jai.crys@gmail.com>
License-Expression: MIT
Project-URL: Homepage, https://github.com/csv-cleaner/csv-cleaner
Project-URL: Documentation, https://github.com/csv-cleaner/csv-cleaner#readme
Project-URL: Repository, https://github.com/csv-cleaner/csv-cleaner
Project-URL: Bug Tracker, https://github.com/csv-cleaner/csv-cleaner/issues
Keywords: csv,data-cleaning,pandas,ai,machine-learning
Classifier: Development Status :: 4 - Beta
Classifier: Intended Audience :: Developers
Classifier: Intended Audience :: End Users/Desktop
Classifier: Intended Audience :: Information Technology
Classifier: Operating System :: OS Independent
Classifier: Programming Language :: Python :: 3
Classifier: Programming Language :: Python :: 3.8
Classifier: Programming Language :: Python :: 3.9
Classifier: Programming Language :: Python :: 3.10
Classifier: Programming Language :: Python :: 3.11
Classifier: Programming Language :: Python :: 3.12
Classifier: Topic :: Software Development :: Libraries :: Python Modules
Classifier: Topic :: Utilities
Requires-Python: >=3.8
License-File: LICENSE
Requires-Dist: pandas>=2.0.0
Requires-Dist: numpy>=1.24.0
Requires-Dist: pyjanitor>=0.24.0
Requires-Dist: click>=8.1.0
Requires-Dist: pyyaml>=6.0
Requires-Dist: tqdm>=4.65.0
Provides-Extra: ai
Requires-Dist: openai>=1.0.0; extra == "ai"
Requires-Dist: anthropic>=0.7.0; extra == "ai"
Requires-Dist: ollama>=0.1.0; extra == "ai"
Provides-Extra: performance
Requires-Dist: polars>=0.19.0; extra == "performance"
Requires-Dist: dask>=2023.0.0; extra == "performance"
Provides-Extra: ml
Requires-Dist: dedupe>=2.1.0; extra == "ml"
Provides-Extra: dev
Requires-Dist: pytest>=7.0.0; extra == "dev"
Requires-Dist: pytest-asyncio>=0.21.0; extra == "dev"
Requires-Dist: black>=22.0.0; extra == "dev"
Requires-Dist: flake8>=5.0.0; extra == "dev"
Requires-Dist: mypy>=1.0.0; extra == "dev"
Requires-Dist: pre-commit>=3.0.0; extra == "dev"
Dynamic: license-file
